chatGPTMidJourneyPrompt/__init__.py
chatGPTMidJourneyPrompt/mjPrompt.py
chatGPTMidJourneyPrompt/prompt_models/artistic.txt
chatGPTMidJourneyPrompt/prompt_models/weights.txt
chatGPTMidJourneyPrompt/settings/V4.py
chatGPTMidJourneyPrompt/settings/V5.py
chatGPTMidJourneyPrompt/settings/default.py
chatGPTMidJourneyPrompt/settings/niji.py
chatGPTMidJourneyPrompt/settings/testp.py
chatGPTMidJourneyPrompt-2.0.3.dist-info/LICENSE
chatGPTMidJourneyPrompt-2.0.3.dist-info/METADATA
chatGPTMidJourneyPrompt-2.0.3.dist-info/WHEEL
chatGPTMidJourneyPrompt-2.0.3.dist-info/top_level.txt
chatGPTMidJourneyPrompt-2.0.3.dist-info/RECORD
