Metadata-Version: 2.1
Name: chatGPTMidJourneyPrompt
Version: 2.0.3
Summary: This is a ChatGPT based prompt generation model for MidJorney. The purpose of this model is to simplify the creation of images and increase their creativity. By introducing a partial hint, ChatGPT creates a follow-up that can be used to stimulate creativity and provide new ideas.
Author-email: awekrx <d.ipatov.v@gmail.com>
Project-URL: Homepage, https://github.com/awekrx/ChatGPT-MidJourney-prompt
Project-URL: Bug Tracker, https://github.com/awekrx/ChatGPT-MidJourney-prompt/issues
Classifier: Programming Language :: Python :: 3
Classifier: License :: OSI Approved :: MIT License
Classifier: Operating System :: OS Independent
Requires-Python: >=3.9
License-File: LICENSE
